{
  "allquestion": [
    
    {
      "dapan": "C",
      "link": "https://i.postimg.cc/3RZNHQ4d/10-1-C.png",
      "giaithich": "Trẻ em rất mong đợi ngày này vì thường được người lớn tặng đồ chơi, thường là đèn ông sao, mặt nạ, đèn kéo quân, tò he..."
    },
    {
      "dapan": "B",
      "link": "https://i.postimg.cc/wx0MfHYr/10-2-B.png",
      "giaithich": "Số 100 trong bảng La Mã là C"
    },
    {
      "dapan": "B",
      "link": "https://i.postimg.cc/fy2bJ7vs/10-3-B.png",
      "giaithich": "Thành phố Pleiku thuộc tỉnh Gia Lai"
    },
    {
      "dapan": "D",
      "link": "https://i.postimg.cc/8Pc5x31z/10-4-D.png",
      "giaithich": "Nhóm máu AB"
    },
    {
      "dapan": "A",
      "link": "https://i.postimg.cc/brNJyVkL/10-5-A.png",
      "giaithich": "S-Fone từng là thương hiệu của Trung tâm điện thoại di động CDMA S-Telecom"
    }
    
  ]
}
